cacheia_api/__init__.py
cacheia_api/__main__.py
cacheia_api/settings.py
cacheia_api/app/__init__.py
cacheia_api/app/routes.py
cacheia_api/app/schemas.py
cacheia_api-1.0.0.post3.dist-info/METADATA
cacheia_api-1.0.0.post3.dist-info/WHEEL
cacheia_api-1.0.0.post3.dist-info/top_level.txt
cacheia_api-1.0.0.post3.dist-info/RECORD
