Metadata-Version: 2.1
Name: cacheia_api
Version: 1.0.0.post3
Summary: FastAPI based API for cache service that allows invalidation and other shenanigans
Author-email: TeiaLabs <contato@teialabs.com>
Keywords: api,cache,fastapi,middleware
Requires-Python: >=3.12
Requires-Dist: fastapi ~=0.111
Requires-Dist: uvicorn ~=0.30
Provides-Extra: core
Requires-Dist: cacheia[schemas] ==1.0.0 ; extra == 'core'
Provides-Extra: dev
Requires-Dist: black <25,>=24 ; extra == 'dev'
Requires-Dist: isort <6,>=5 ; extra == 'dev'
Requires-Dist: pytest <9,>=8 ; extra == 'dev'
Requires-Dist: httpx ~=0.27 ; extra == 'dev'
